acp/__init__.py
acp/experiments.py
acp/methods.py
acp/models.py
acp/others.py
acp/utils.py
acp/wrapper.py
third_party/__init__.py
third_party/RAPS/RAPS_conformal.py
third_party/RAPS/__init__.py
approx_cp-0.0.2.dist-info/METADATA
approx_cp-0.0.2.dist-info/WHEEL
approx_cp-0.0.2.dist-info/top_level.txt
approx_cp-0.0.2.dist-info/RECORD
