Metadata-Version: 2.1
Name: approx-cp
Version: 0.0.2
Summary: Python implementation of Approximate full Conformal Prediction (ACP)
Home-page: https://github.com/cambridge-mlg/acp
Author: Javier Abad
Author-email: javier.abadmartinez@ai.ethz.ch
Project-URL: Paper, https://arxiv.org/abs/2202.01315
Keywords: machine learning,AAAI,conformal prediction
Classifier: License :: OSI Approved :: MIT License
Classifier: Programming Language :: Python :: 3
Classifier: Operating System :: OS Independent
Requires-Python: >=3
Requires-Dist: numpy
Requires-Dist: torch
Requires-Dist: torchvision
Requires-Dist: torchaudio
Requires-Dist: pandas
Requires-Dist: tqdm
Requires-Dist: matplotlib
Requires-Dist: keras
Requires-Dist: folktables
Requires-Dist: scipy
Requires-Dist: scikit-learn
Requires-Dist: seaborn
